Verilog/S1-T19-ChaCha.v
//quarter round generator module
module qrg (
    input A, B, C, D,         // 4 inputs
    output reg a, b, c, d     // 4 outputs
);

    always @(*) begin
        case ({A, B, C, D})
            4'b0000: {a, b, c, d} = 4'b0000;
            4'b0001: {a, b, c, d} = 4'b1010;
            4'b0010: {a, b, c, d} = 4'b1101;
            4'b0011: {a, b, c, d} = 4'b0111;
            4'b0100: {a, b, c, d} = 4'b1110;
            4'b0101: {a, b, c, d} = 4'b0100;
            4'b0110: {a, b, c, d} = 4'b0011;
            4'b0111: {a, b, c, d} = 4'b1001;
            4'b1000: {a, b, c, d} = 4'b0101;
            4'b1001: {a, b, c, d} = 4'b1111;
            4'b1010: {a, b, c, d} = 4'b1000;
            4'b1011: {a, b, c, d} = 4'b0010;
            4'b1100: {a, b, c, d} = 4'b1011;
            4'b1101: {a, b, c, d} = 4'b0001;
            4'b1110: {a, b, c, d} = 4'b0110;
            4'b1111: {a, b, c, d} = 4'b1100;
        endcase
    end
endmodule
//2-bit counter module
module two_bit_counter (
    input wire clk,         // Clock input
    input wire reset,       // Asynchronous reset input
    input wire [1:0] init_value, // Initial value input
    input wire lock,        // Lock input to set initial value
    output reg [1:0] count  // 2-bit counter output
);

    always @(posedge clk or posedge reset or posedge lock) begin
        if (reset) begin
            count <= 2'b00;  // Reset counter to 0
        end else if (lock) begin
            count <= init_value;  // Set counter to initial value
        end else begin
            count <= count + 1;  // Increment counter
        end
    end

endmodule
//key stream generator module
module ksg (
    input [3:0] constant,
    input [7:0] key,
    input [1:0] counter,
    input [1:0] nonce,
    output [3:0] final_out1,
    output [3:0] final_out2,
    output [3:0] final_out3,
    output [3:0] final_out4
);
    wire [3:0] qrg_out1, qrg_out2, qrg_out3, qrg_out4;

    // First round of qrg instances with reversed input bits
    qrg qrg1 (
        .A(constant[3]), // Reversed
        .B(key[7]),      // Reversed
        .C(key[6]),      // Reversed
        .D(counter[1]),  // Reversed
        .a(qrg_out1[0]),
        .b(qrg_out1[1]),
        .c(qrg_out1[2]),
        .d(qrg_out1[3])
    );

    qrg qrg2 (
        .A(constant[2]), // Reversed
        .B(key[5]),      // Reversed
        .C(key[4]),      // Reversed
        .D(counter[0]),  // Reversed
        .a(qrg_out2[0]),
        .b(qrg_out2[1]),
        .c(qrg_out2[2]),
        .d(qrg_out2[3])
    );

    qrg qrg3 (
        .A(constant[1]), // Reversed
        .B(key[3]),      // Reversed
        .C(key[2]),      // Reversed
        .D(nonce[1]),    // Reversed
        .a(qrg_out3[0]),
        .b(qrg_out3[1]),
        .c(qrg_out3[2]),
        .d(qrg_out3[3])
    );

    qrg qrg4 (
        .A(constant[0]), // Reversed
        .B(key[1]),      // Reversed
        .C(key[0]),      // Reversed
        .D(nonce[0]),    // Reversed
        .a(qrg_out4[0]),
        .b(qrg_out4[1]),
        .c(qrg_out4[2]),
        .d(qrg_out4[3])
    );

    // Second round of qrg instances with cyclic input bits
    qrg qrg5 (
        .A(qrg_out1[0]),
        .B(qrg_out2[1]),
        .C(qrg_out3[2]),
        .D(qrg_out4[3]),
        .a(final_out1[3]),
        .b(final_out1[2]),
        .c(final_out1[1]),
        .d(final_out1[0])
    );

    qrg qrg6 (
        .A(qrg_out1[1]),
        .B(qrg_out2[2]),
        .C(qrg_out3[3]),
        .D(qrg_out4[0]),
        .a(final_out2[3]),
        .b(final_out2[2]),
        .c(final_out2[1]),
        .d(final_out2[0])
    );

    qrg qrg7 (
        .A(qrg_out1[2]),
        .B(qrg_out2[3]),
        .C(qrg_out3[0]),
        .D(qrg_out4[1]),
        .a(final_out3[3]),
        .b(final_out3[2]),
        .c(final_out3[1]),
        .d(final_out3[0])
    );

    qrg qrg8 (
        .A(qrg_out1[3]),
        .B(qrg_out2[0]),
        .C(qrg_out3[1]),
        .D(qrg_out4[2]),
        .a(final_out4[3]),
        .b(final_out4[2]),
        .c(final_out4[1]),
        .d(final_out4[0])
    );

endmodule
//plain text input module
module plain_text (
    input wire plain_text_input1,       // First input bit
    input wire plain_text_input2,       // Second input bit
    output wire flag,      // Flag output, set to 1 if any input bit is 1
    output wire bit_value  // Output the bit value that is set
);

    // Set the flag if any of the input bits is 1
    or(flag,plain_text_input1,plain_text_input2);

    // Output the bit value that is set (1 if bit1 is set, otherwise 0)
    assign bit_value = plain_text_input1 ? 1'b1 : 1'b0;

endmodule

//bit selector for final output
module four_counter (
    input clk,                // Clock input
    input reset,              // Reset input
    input lock,               // Lock signal
    output reg [3:0] count    // 4-bit counter output
);

    always @(posedge clk or posedge reset) begin
        if (reset) begin
            count <= 4'b0000;  // Reset counter to 0
        end else if (lock) begin
            count <= 4'b1111;  // Set counter to 16 (4'b1111)
        end else begin
            count <= count + 1; // Increment counter
        end
    end

endmodule

module bit_selector (
    input [15:0] data_in,     // 16-bit input data
    input [3:0] clock_in,     // 4-bit input clock
    output reg out            // Selected bit output
);

    // Decoder logic
    always @(*) begin
        case (clock_in)
            4'b0000: out = data_in[15];  // Clock 0 selects last bit
            4'b0001: out = data_in[14];  // Clock 1 selects second-to-last bit
            4'b0010: out = data_in[13];
            4'b0011: out = data_in[12];
            4'b0100: out = data_in[11];
            4'b0101: out = data_in[10];
            4'b0110: out = data_in[9];
            4'b0111: out = data_in[8];
            4'b1000: out = data_in[7];
            4'b1001: out = data_in[6];
            4'b1010: out = data_in[5];
            4'b1011: out = data_in[4];
            4'b1100: out = data_in[3];
            4'b1101: out = data_in[2];
            4'b1110: out = data_in[1];
            4'b1111: out = data_in[0];  // Clock 15 selects first bit
            default: out = 1'b0;
        endcase
    end

endmodule
//main module
module main (
    input wire clk,
    input wire reset,
    input wire [7:0] key,
    input wire [1:0] nonce,
    input wire  plain_text_input1,
    input wire plain_text_input2,
    input wire [1:0] init_value,
    input wire lock,  // Lock input for both counter and bit selector
    output wire final_output
);

    // Internal signals
    wire [1:0] counter_output;
    wire [3:0] ksg_output1, ksg_output2, ksg_output3, ksg_output4;
    wire [3:0] constant = 4'b1101;

    wire bit_selector_output;
    wire plain_text_flag;
    wire plain_text_bit_value;

    // Instantiate the two_bit_counter
    two_bit_counter counter_uut (
        .clk(plain_text_flag),
        .reset(reset),
        .init_value(init_value),
        .lock(lock),
        .count(counter_output)
    );

    // Instantiate the ksg module
    ksg ksg_uut (
        .constant(constant),
        .key(key),
        .counter(counter_output),
        .nonce(nonce),
        .final_out1(ksg_output1),
        .final_out2(ksg_output2),
        .final_out3(ksg_output3),
        .final_out4(ksg_output4)
    );

    // Instantiate the plain-text input module
    plain_text plain_text_uut (
        .plain_text_input1(plain_text_input1),
        .plain_text_input2(plain_text_input2),
        .flag(plain_text_flag),
        .bit_value(plain_text_bit_value)
    );

    // Concatenate ksg outputs to form a 16-bit input for bit selector
    wire [15:0] ksg_combined_output = {ksg_output1, ksg_output2, ksg_output3, ksg_output4};
    wire [3:0] four_out;

    four_counter counter_4 (
        .clk(plain_text_flag),
        .reset(reset),
        .lock(lock),
        .count(four_out)
    );

    // Instantiate the bit selector
    bit_selector bit_selector_uut (
        .data_in(ksg_combined_output),
        .clock_in(four_out),  // Use counter output as part of clock input
        // .lock(lock),
        .out(bit_selector_output)
    );

    // XOR the bit selector output with the plain-text bit value
    assign final_output = bit_selector_output ^ plain_text_bit_value;

endmodule

Verilog/S1-T19-ChaCha_tb.v
//testbench for main module
module main_tb;
    // Inputs
    reg clk;
    reg reset;
    reg [7:0] key;
    reg [1:0] nonce;
    reg  plain_text_input1;
    reg plain_text_input2;
    reg lock;
    reg [1:0] init_value;

    // Outputs
    wire final_output;

    // Instantiate the main module
    main uut (
        .clk(clk),
        .reset(reset),
        .key(key),
        .nonce(nonce),
        .plain_text_input1(plain_text_input1),
        .plain_text_input2(plain_text_input2),
        .init_value(init_value),
        .lock(lock),
        .final_output(final_output)
    );

    // Clock generation
    initial begin
        clk = 0;
        forever #5 clk = ~clk; // 10ns period clock
    end

    // Test sequence
    initial begin
        // Initialize inputs
        reset = 1;
        key = 8'h00;
        nonce = 2'b00;
        plain_text_input1 = 1'b0;
        plain_text_input2 = 1'b0;
        lock = 0;
        init_value = 2'b00;

        // Dump waveform data
        $dumpfile("S1-T19-ChaCha.vcd");
        $dumpvars(0, main_tb);

        // Apply test vectors
        #10 reset=0;
        #10 key = 8'b11011011; nonce = 2'b11; lock = 1;init_value = 2'b01;
        #10 lock = 0;
        #10 plain_text_input1 = 1'b1;
        #10 plain_text_input1 = 1'b0;
        #10 plain_text_input1 = 1'b1;
        #10 plain_text_input1 = 1'b0;
        #10 plain_text_input1 = 1'b1;
        #10 plain_text_input1 = 1'b0;

        // #50 reset = 1;
        #10 reset = 0; key = 8'b11011011; nonce = 2'b00; plain_text_input1 = 1'b0;;

        // Finish simulation
        #100 $finish;
    end

    initial begin
        // Monitor the outputs
        $monitor("At time %t, key = %b, nonce = %b, plain_text_input1 = %b,plain_text_input0 = %b, lock = %b, counter_init_value = %b, final_output = %b",
                 $time, key, nonce, plain_text_input1,plain_text_input2, lock, init_value,final_output);
    end
endmodule

Verilog/S1-T19-ChaCha.vcd
$date
	Mon Oct 14 16:53:23 2024
$end
$version
	Icarus Verilog
$end
$timescale
	1s
$end
$scope module main_tb $end
$var wire 1 ! final_output $end
$var reg 1 " clk $end
$var reg 2 # init_value [1:0] $end
$var reg 8 $ key [7:0] $end
$var reg 1 % lock $end
$var reg 2 & nonce [1:0] $end
$var reg 1 ' plain_text_input1 $end
$var reg 1 ( plain_text_input2 $end
$var reg 1 ) reset $end
$scope module uut $end
$var wire 1 " clk $end
$var wire 4 * constant [3:0] $end
$var wire 1 ! final_output $end
$var wire 2 + init_value [1:0] $end
$var wire 8 , key [7:0] $end
$var wire 1 % lock $end
$var wire 2 - nonce [1:0] $end
$var wire 1 ' plain_text_input1 $end
$var wire 1 ( plain_text_input2 $end
$var wire 1 ) reset $end
$var wire 1 . plain_text_flag $end
$var wire 1 / plain_text_bit_value $end
$var wire 4 0 ksg_output4 [3:0] $end
$var wire 4 1 ksg_output3 [3:0] $end
$var wire 4 2 ksg_output2 [3:0] $end
$var wire 4 3 ksg_output1 [3:0] $end
$var wire 16 4 ksg_combined_output [15:0] $end
$var wire 4 5 four_out [3:0] $end
$var wire 2 6 counter_output [1:0] $end
$var wire 1 7 bit_selector_output $end
$scope module bit_selector_uut $end
$var wire 16 8 data_in [15:0] $end
$var wire 4 9 clock_in [3:0] $end
$var reg 1 7 out $end
$upscope $end
$scope module counter_4 $end
$var wire 1 % lock $end
$var wire 1 ) reset $end
$var wire 1 . clk $end
$var reg 4 : count [3:0] $end
$upscope $end
$scope module counter_uut $end
$var wire 2 ; init_value [1:0] $end
$var wire 1 % lock $end
$var wire 1 ) reset $end
$var wire 1 . clk $end
$var reg 2 < count [1:0] $end
$upscope $end
$scope module ksg_uut $end
$var wire 4 = constant [3:0] $end
$var wire 2 > counter [1:0] $end
$var wire 8 ? key [7:0] $end
$var wire 2 @ nonce [1:0] $end
$var wire 4 A qrg_out4 [3:0] $end
$var wire 4 B qrg_out3 [3:0] $end
$var wire 4 C qrg_out2 [3:0] $end
$var wire 4 D qrg_out1 [3:0] $end
$var wire 4 E final_out4 [3:0] $end
$var wire 4 F final_out3 [3:0] $end
$var wire 4 G final_out2 [3:0] $end
$var wire 4 H final_out1 [3:0] $end
$scope module qrg1 $end
$var wire 1 I A $end
$var wire 1 J B $end
$var wire 1 K C $end
$var wire 1 L D $end
$var reg 1 M a $end
$var reg 1 N b $end
$var reg 1 O c $end
$var reg 1 P d $end
$upscope $end
$scope module qrg2 $end
$var wire 1 Q A $end
$var wire 1 R B $end
$var wire 1 S C $end
$var wire 1 T D $end
$var reg 1 U a $end
$var reg 1 V b $end
$var reg 1 W c $end
$var reg 1 X d $end
$upscope $end
$scope module qrg3 $end
$var wire 1 Y A $end
$var wire 1 Z B $end
$var wire 1 [ C $end
$var wire 1 \ D $end
$var reg 1 ] a $end
$var reg 1 ^ b $end
$var reg 1 _ c $end
$var reg 1 ` d $end
$upscope $end
$scope module qrg4 $end
$var wire 1 a A $end
$var wire 1 b B $end
$var wire 1 c C $end
$var wire 1 d D $end
$var reg 1 e a $end
$var reg 1 f b $end
$var reg 1 g c $end
$var reg 1 h d $end
$upscope $end
$scope module qrg5 $end
$var wire 1 i A $end
$var wire 1 j B $end
$var wire 1 k C $end
$var wire 1 l D $end
$var reg 1 m a $end
$var reg 1 n b $end
$var reg 1 o c $end
$var reg 1 p d $end
$upscope $end
$scope module qrg6 $end
$var wire 1 q A $end
$var wire 1 r B $end
$var wire 1 s C $end
$var wire 1 t D $end
$var reg 1 u a $end
$var reg 1 v b $end
$var reg 1 w c $end
$var reg 1 x d $end
$upscope $end
$scope module qrg7 $end
$var wire 1 y A $end
$var wire 1 z B $end
$var wire 1 { C $end
$var wire 1 | D $end
$var reg 1 } a $end
$var reg 1 ~ b $end
$var reg 1 !" c $end
$var reg 1 "" d $end
$upscope $end
$scope module qrg8 $end
$var wire 1 #" A $end
$var wire 1 $" B $end
$var wire 1 %" C $end
$var wire 1 &" D $end
$var reg 1 '" a $end
$var reg 1 (" b $end
$var reg 1 )" c $end
$var reg 1 *" d $end
$upscope $end
$upscope $end
$scope module plain_text_uut $end
$var wire 1 . flag $end
$var wire 1 ' plain_text_input1 $end
$var wire 1 ( plain_text_input2 $end
$var wire 1 / bit_value $end
$upscope $end
$upscope $end
$upscope $end
$enddefinitions $end
$comment Show the parameter values. $end
$dumpall
$end
#0
$dumpvars
1*"
0)"
1("
0'"
0&"
0%"
0$"
1#"
0""
0!"
1~
0}
1|
0{
1z
0y
1x
0w
1v
0u
0t
0s
0r
1q
0p
0o
1n
0m
1l
0k
1j
0i
1h
0g
1f
0e
0d
0c
0b
1a
0`
0_
0^
0]
0\
0[
0Z
0Y
1X
0W
1V
0U
0T
0S
0R
1Q
1P
0O
1N
0M
0L
0K
0J
1I
b100 H
b101 G
b100 F
b101 E
b1010 D
b1010 C
b0 B
b1010 A
b0 @
b0 ?
b0 >
b1101 =
b0 <
b0 ;
b0 :
b0 9
b100010101000101 8
07
b0 6
b0 5
b100010101000101 4
b100 3
b101 2
b100 1
b101 0
0/
0.
b0 -
b0 ,
b0 +
b1101 *
1)
0(
0'
b0 &
0%
b0 $
b0 #
0"
0!
$end
#5
1"
#10
0"
0)
#15
1"
#20
1'"
0v
1r
1W
1T
b1 6
b1 <
b1 >
1}
1!"
b1111 1
b1111 F
1""
1("
b1101 0
b1101 E
0)"
0u
b1 2
b1 G
0w
b111111101 4
b111111101 8
b0 3
b0 H
0n
1y
0#"
0$"
0j
0z
1%"
1t
0l
1O
b110 D
0P
0U
0V
b100 C
0X
b10 B
1^
1e
b11 A
0h
1\
1d
1J
1K
1S
1Z
1b
1c
0"
b1 #
b1 +
b1 ;
1%
b11 &
b11 -
b11 @
b11011011 $
b11011011 ,
b11011011 ?
#25
1"
#30
0"
0%
#35
1"
#40
17
1n
b101 3
b101 H
1p
0~
b1010 1
b1010 F
0""
0'"
0("
b11 0
b11 E
1)"
1u
1v
b101111110100011 4
b101111110100011 8
b1111 2
b1111 G
1w
1i
0y
1$"
0r
1M
b11 D
0O
1U
b1 C
0W
1L
0T
b1 5
b1 9
b1 :
b10 6
b10 <
b10 >
0!
1.
1/
0"
1'
#45
1"
#50
1!
0.
0/
0"
0'
#55
1"
#60
1'"
1("
b1101 0
b1101 E
0)"
0u
0v
b101000110101101 4
b101000110101101 8
b1 2
b1 G
0w
0$"
1r
0U
b100 C
1W
07
1T
b10 5
b10 9
b10 :
b11 6
b11 <
b11 >
1!
1.
1/
0"
1'
#65
1"
#70
0!
0.
0/
0"
0'
#75
1"
#80
0n
b0 3
b0 H
0p
1~
b1111 1
b1111 F
1""
0'"
0("
b11 0
b11 E
1)"
1u
1v
b111111110011 4
b111111110011 8
b1111 2
b1111 G
1w
0i
1y
1$"
0r
0M
b110 D
1O
1U
b1 C
0W
07
0L
0T
b11 5
b11 9
b11 :
b0 6
b0 <
b0 >
1!
1.
1/
0"
1'
#85
1"
#90
0!
0.
0/
0"
0'
#95
1"
#100
1!
17
0}
0~
b10 1
b10 F
0""
1m
1n
b1101 3
b1101 H
1p
0u
b101 2
b101 G
0w
1'"
b1101010100101001 4
b1101010100101001 8
b1001 0
b1001 E
0)"
1{
1k
0t
1&"
1]
b111 B
1_
0e
b110 A
1g
0\
0d
0"
b0 &
b0 -
b0 @
